{
  "abilities": [
    {
      "type": "cobblemon:hidden",
      "ability": "cobblemon:symbiosis"
    },
    {
      "type": "cobblemon:common",
      "ability": "cobblemon:flowerveil"
    }
  ],
  "baseExperienceYield": 61,
  "baseFriendship": 70,
  "baseStats": {
    "cobblemon:attack": 38,
    "cobblemon:defence": 39,
    "cobblemon:hp": 44,
    "cobblemon:special_attack": 61,
    "cobblemon:special_defence": 79,
    "cobblemon:speed": 42
  },
  "behaviour": {
    "idle": {
      "pointsAtSpawn": false
    },
    "moving": {
      "fly": {
        "flySpeedHorizontal": "0.3"
      },
      "swim": {
        "swimSpeed": "0.3"
      },
      "walk": {
        "canWalk": false,
        "walkSpeed": "0.35"
      }
    }
  },
  "catchRate": 225,
  "dynamaxBlocked": false,
  "eggCycles": 20,
  "eggGroups": [
    "FAIRY"
  ],
  "evYield": {
    "cobblemon:special_defence": 1
  },
  "experienceGroup": "cobblemon:medium_fast",
  "height": 0.1,
  "hitbox": {
    "fixed": true,
    "height": 1.0,
    "width": 1.0
  },
  "maleRatio": 0.0,
  "moves": [
    {
      "type": "cobblemon:level",
      "level": 1,
      "move": "cobblemon:vinewhip"
    },
    {
      "type": "cobblemon:level",
      "level": 1,
      "move": "cobblemon:tackle"
    },
    {
      "type": "cobblemon:level",
      "level": 6,
      "move": "cobblemon:fairywind"
    },
    {
      "type": "cobblemon:level",
      "level": 10,
      "move": "cobblemon:luckychant"
    },
    {
      "type": "cobblemon:level",
      "level": 10,
      "move": "cobblemon:safeguard"
    },
    {
      "type": "cobblemon:level",
      "level": 15,
      "move": "cobblemon:razorleaf"
    },
    {
      "type": "cobblemon:level",
      "level": 20,
      "move": "cobblemon:wish"
    },
    {
      "type": "cobblemon:level",
      "level": 22,
      "move": "cobblemon:magicalleaf"
    },
    {
      "type": "cobblemon:level",
      "level": 24,
      "move": "cobblemon:grassyterrain"
    },
    {
      "type": "cobblemon:level",
      "level": 28,
      "move": "cobblemon:petalblizzard"
    },
    {
      "type": "cobblemon:level",
      "level": 33,
      "move": "cobblemon:synthesis"
    },
    {
      "type": "cobblemon:level",
      "level": 33,
      "move": "cobblemon:aromatherapy"
    },
    {
      "type": "cobblemon:level",
      "level": 37,
      "move": "cobblemon:mistyterrain"
    },
    {
      "type": "cobblemon:level",
      "level": 41,
      "move": "cobblemon:moonblast"
    },
    {
      "type": "cobblemon:level",
      "level": 45,
      "move": "cobblemon:petaldance"
    },
    {
      "type": "cobblemon:level",
      "level": 48,
      "move": "cobblemon:solarbeam"
    },
    {
      "type": "cobblemon:tutor",
      "move": "cobblemon:endeavor"
    },
    {
      "type": "cobblemon:tm",
      "move": "cobblemon:attract"
    },
    {
      "type": "cobblemon:tutor",
      "move": "cobblemon:seedbomb"
    },
    {
      "type": "cobblemon:tutor",
      "move": "cobblemon:helpinghand"
    },
    {
      "type": "cobblemon:tutor",
      "move": "cobblemon:healbell"
    },
    {
      "type": "cobblemon:tm",
      "move": "cobblemon:sleeptalk"
    },
    {
      "type": "cobblemon:tm",
      "move": "cobblemon:toxic"
    },
    {
      "type": "cobblemon:tm",
      "move": "cobblemon:disarmingvoice"
    },
    {
      "type": "cobblemon:tutor",
      "move": "cobblemon:gigadrain"
    },
    {
      "type": "cobblemon:tm",
      "move": "cobblemon:sleeptalk"
    },
    {
      "type": "cobblemon:tm",
      "move": "cobblemon:endeavor"
    },
    {
      "type": "cobblemon:tm",
      "move": "cobblemon:seedbomb"
    },
    {
      "type": "cobblemon:tm",
      "move": "cobblemon:echoedvoice"
    },
    {
      "type": "cobblemon:egg",
      "move": "cobblemon:tearfullook"
    },
    {
      "type": "cobblemon:tm",
      "move": "cobblemon:endure"
    },
    {
      "type": "cobblemon:tm",
      "move": "cobblemon:terablast"
    },
    {
      "type": "cobblemon:tm",
      "move": "cobblemon:energyball"
    },
    {
      "type": "cobblemon:tm",
      "move": "cobblemon:rest"
    },
    {
      "type": "cobblemon:tm",
      "move": "cobblemon:round"
    },
    {
      "type": "cobblemon:tm",
      "move": "cobblemon:round"
    },
    {
      "type": "cobblemon:tm",
      "move": "cobblemon:grassknot"
    },
    {
      "type": "cobblemon:tm",
      "move": "cobblemon:mistyterrain"
    },
    {
      "type": "cobblemon:tm",
      "move": "cobblemon:psychic"
    },
    {
      "type": "cobblemon:tutor",
      "move": "cobblemon:magiccoat"
    },
    {
      "type": "cobblemon:tm",
      "move": "cobblemon:swagger"
    },
    {
      "type": "cobblemon:tm",
      "move": "cobblemon:confide"
    },
    {
      "type": "cobblemon:tm",
      "move": "cobblemon:hiddenpower"
    },
    {
      "type": "cobblemon:tm",
      "move": "cobblemon:substitute"
    },
    {
      "type": "cobblemon:tm",
      "move": "cobblemon:helpinghand"
    },
    {
      "type": "cobblemon:tm",
      "move": "cobblemon:raindance"
    },
    {
      "type": "cobblemon:tm",
      "move": "cobblemon:facade"
    },
    {
      "type": "cobblemon:tm",
      "move": "cobblemon:magicalleaf"
    },
    {
      "type": "cobblemon:tm",
      "move": "cobblemon:rest"
    },
    {
      "type": "cobblemon:tm",
      "move": "cobblemon:trailblaze"
    },
    {
      "type": "cobblemon:tm",
      "move": "cobblemon:sleeptalk"
    },
    {
      "type": "cobblemon:egg",
      "move": "cobblemon:endeavor"
    },
    {
      "type": "cobblemon:tm",
      "move": "cobblemon:return"
    },
    {
      "type": "cobblemon:tutor",
      "move": "cobblemon:synthesis"
    },
    {
      "type": "cobblemon:tm",
      "move": "cobblemon:alluringvoice"
    },
    {
      "type": "cobblemon:tutor",
      "move": "cobblemon:seedbomb"
    },
    {
      "type": "cobblemon:tm",
      "move": "cobblemon:grassyterrain"
    },
    {
      "type": "cobblemon:tutor",
      "move": "cobblemon:covet"
    },
    {
      "type": "cobblemon:egg",
      "move": "cobblemon:captivate"
    },
    {
      "type": "cobblemon:tm",
      "move": "cobblemon:secretpower"
    },
    {
      "type": "cobblemon:tm",
      "move": "cobblemon:toxic"
    },
    {
      "type": "cobblemon:tm",
      "move": "cobblemon:doubleteam"
    },
    {
      "type": "cobblemon:tm",
      "move": "cobblemon:rest"
    },
    {
      "type": "cobblemon:tm",
      "move": "cobblemon:calmmind"
    },
    {
      "type": "cobblemon:tm",
      "move": "cobblemon:safeguard"
    },
    {
      "type": "cobblemon:egg",
      "move": "cobblemon:captivate"
    },
    {
      "type": "cobblemon:tutor",
      "move": "cobblemon:covet"
    },
    {
      "type": "cobblemon:tutor",
      "move": "cobblemon:healbell"
    },
    {
      "type": "cobblemon:tm",
      "move": "cobblemon:echoedvoice"
    },
    {
      "type": "cobblemon:tm",
      "move": "cobblemon:drainingkiss"
    },
    {
      "type": "cobblemon:egg",
      "move": "cobblemon:camouflage"
    },
    {
      "type": "cobblemon:tm",
      "move": "cobblemon:lightscreen"
    },
    {
      "type": "cobblemon:tutor",
      "move": "cobblemon:magiccoat"
    },
    {
      "type": "cobblemon:tutor",
      "move": "cobblemon:afteryou"
    },
    {
      "type": "cobblemon:tm",
      "move": "cobblemon:protect"
    },
    {
      "type": "cobblemon:tm",
      "move": "cobblemon:chillingwater"
    },
    {
      "type": "cobblemon:tm",
      "move": "cobblemon:protect"
    },
    {
      "type": "cobblemon:tm",
      "move": "cobblemon:energyball"
    },
    {
      "type": "cobblemon:tm",
      "move": "cobblemon:substitute"
    },
    {
      "type": "cobblemon:tm",
      "move": "cobblemon:gigadrain"
    },
    {
      "type": "cobblemon:tm",
      "move": "cobblemon:energyball"
    },
    {
      "type": "cobblemon:tm",
      "move": "cobblemon:sunnyday"
    },
    {
      "type": "cobblemon:tutor",
      "move": "cobblemon:allyswitch"
    },
    {
      "type": "cobblemon:tm",
      "move": "cobblemon:solarbeam"
    },
    {
      "type": "cobblemon:tutor",
      "move": "cobblemon:snore"
    },
    {
      "type": "cobblemon:tm",
      "move": "cobblemon:frustration"
    },
    {
      "type": "cobblemon:tutor",
      "move": "cobblemon:worryseed"
    },
    {
      "type": "cobblemon:tm",
      "move": "cobblemon:psychic"
    },
    {
      "type": "cobblemon:tutor",
      "move": "cobblemon:helpinghand"
    },
    {
      "type": "cobblemon:tm",
      "move": "cobblemon:petalblizzard"
    },
    {
      "type": "cobblemon:tutor",
      "move": "cobblemon:endeavor"
    },
    {
      "type": "cobblemon:tm",
      "move": "cobblemon:grassknot"
    },
    {
      "type": "cobblemon:tm",
      "move": "cobblemon:solarbeam"
    },
    {
      "type": "cobblemon:tm",
      "move": "cobblemon:dazzlinggleam"
    },
    {
      "type": "cobblemon:tm",
      "move": "cobblemon:batonpass"
    },
    {
      "type": "cobblemon:tm",
      "move": "cobblemon:charm"
    },
    {
      "type": "cobblemon:tutor",
      "move": "cobblemon:gigadrain"
    },
    {
      "type": "cobblemon:tm",
      "move": "cobblemon:solarbeam"
    },
    {
      "type": "cobblemon:tm",
      "move": "cobblemon:naturepower"
    },
    {
      "type": "cobblemon:tm",
      "move": "cobblemon:raindance"
    },
    {
      "type": "cobblemon:tm",
      "move": "cobblemon:substitute"
    },
    {
      "type": "cobblemon:tm",
      "move": "cobblemon:attract"
    },
    {
      "type": "cobblemon:tm",
      "move": "cobblemon:swagger"
    },
    {
      "type": "cobblemon:tm",
      "move": "cobblemon:storedpower"
    },
    {
      "type": "cobblemon:tm",
      "move": "cobblemon:calmmind"
    },
    {
      "type": "cobblemon:tm",
      "move": "cobblemon:return"
    },
    {
      "type": "cobblemon:tm",
      "move": "cobblemon:raindance"
    },
    {
      "type": "cobblemon:tutor",
      "move": "cobblemon:afteryou"
    },
    {
      "type": "cobblemon:tm",
      "move": "cobblemon:frustration"
    },
    {
      "type": "cobblemon:tutor",
      "move": "cobblemon:worryseed"
    },
    {
      "type": "cobblemon:tutor",
      "move": "cobblemon:snore"
    },
    {
      "type": "cobblemon:egg",
      "move": "cobblemon:tearfullook"
    },
    {
      "type": "cobblemon:tm",
      "move": "cobblemon:dazzlinggleam"
    },
    {
      "type": "cobblemon:tm",
      "move": "cobblemon:grassknot"
    },
    {
      "type": "cobblemon:tm",
      "move": "cobblemon:dazzlinggleam"
    },
    {
      "type": "cobblemon:tm",
      "move": "cobblemon:facade"
    },
    {
      "type": "cobblemon:tm",
      "move": "cobblemon:swift"
    },
    {
      "type": "cobblemon:tm",
      "move": "cobblemon:confide"
    },
    {
      "type": "cobblemon:tm",
      "move": "cobblemon:facade"
    },
    {
      "type": "cobblemon:egg",
      "move": "cobblemon:copycat"
    },
    {
      "type": "cobblemon:tm",
      "move": "cobblemon:hiddenpower"
    },
    {
      "type": "cobblemon:tm",
      "move": "cobblemon:safeguard"
    },
    {
      "type": "cobblemon:egg",
      "move": "cobblemon:copycat"
    },
    {
      "type": "cobblemon:tm",
      "move": "cobblemon:sunnyday"
    },
    {
      "type": "cobblemon:tm",
      "move": "cobblemon:calmmind"
    },
    {
      "type": "cobblemon:tm",
      "move": "cobblemon:naturepower"
    },
    {
      "type": "cobblemon:tutor",
      "move": "cobblemon:synthesis"
    },
    {
      "type": "cobblemon:tm",
      "move": "cobblemon:pollenpuff"
    },
    {
      "type": "cobblemon:tm",
      "move": "cobblemon:protect"
    },
    {
      "type": "cobblemon:tm",
      "move": "cobblemon:doubleteam"
    },
    {
      "type": "cobblemon:tm",
      "move": "cobblemon:psychic"
    },
    {
      "type": "cobblemon:egg",
      "move": "cobblemon:camouflage"
    },
    {
      "type": "cobblemon:tm",
      "move": "cobblemon:flash"
    },
    {
      "type": "cobblemon:egg",
      "move": "cobblemon:copycat"
    },
    {
      "type": "cobblemon:tm",
      "move": "cobblemon:sunnyday"
    }
  ],
  "nationalPokedexNumber": 669,
  "primaryType": "cobblemon:fairy",
  "shoulderEffects": [],
  "shoulderMountable": true,
  "weight": 0.1
}