{
  "abilities": [
    {
      "type": "cobblemon:hidden",
      "ability": "cobblemon:runaway"
    },
    {
      "type": "cobblemon:common",
      "ability": "cobblemon:shedskin"
    }
  ],
  "baseExperienceYield": 39,
  "baseFriendship": 70,
  "baseStats": {
    "cobblemon:attack": 25,
    "cobblemon:defence": 41,
    "cobblemon:hp": 37,
    "cobblemon:special_attack": 25,
    "cobblemon:special_defence": 41,
    "cobblemon:speed": 25
  },
  "behaviour": {
    "idle": {
      "pointsAtSpawn": false
    },
    "moving": {
      "fly": {
        "flySpeedHorizontal": "0.3"
      },
      "swim": {
        "swimSpeed": "0.3"
      },
      "walk": {
        "canWalk": false,
        "walkSpeed": "0.35"
      }
    }
  },
  "catchRate": 255,
  "dynamaxBlocked": false,
  "eggCycles": 15,
  "eggGroups": [
    "BUG"
  ],
  "evYield": {
    "cobblemon:defence": 1
  },
  "evolutions": [
    {
      "type": "cobblemon:level_up",
      "consumeHeldItem": false,
      "id": "kricketot_kricketune",
      "learnableMoves": "cobblemon:furycutter",
      "permanent": true,
      "requirements": [
        {
          "type": "cobblemon:level",
          "maxLevel": 10,
          "minLevel": 10
        }
      ],
      "result": "kricketune"
    }
  ],
  "experienceGroup": "cobblemon:medium_slow",
  "height": 0.3,
  "hitbox": {
    "fixed": true,
    "height": 1.0,
    "width": 1.0
  },
  "maleRatio": 0.5,
  "moves": [
    {
      "type": "cobblemon:level",
      "level": 1,
      "move": "cobblemon:bide"
    },
    {
      "type": "cobblemon:level",
      "level": 1,
      "move": "cobblemon:tackle"
    },
    {
      "type": "cobblemon:level",
      "level": 1,
      "move": "cobblemon:growl"
    },
    {
      "type": "cobblemon:level",
      "level": 6,
      "move": "cobblemon:strugglebug"
    },
    {
      "type": "cobblemon:level",
      "level": 16,
      "move": "cobblemon:bugbite"
    },
    {
      "type": "cobblemon:tm",
      "move": "cobblemon:strugglebug"
    },
    {
      "type": "cobblemon:tutor",
      "move": "cobblemon:strugglebug"
    },
    {
      "type": "cobblemon:tutor",
      "move": "cobblemon:mudslap"
    },
    {
      "type": "cobblemon:tutor",
      "move": "cobblemon:bugbite"
    },
    {
      "type": "cobblemon:tutor",
      "move": "cobblemon:snore"
    },
    {
      "type": "cobblemon:tm",
      "move": "cobblemon:skittersmack"
    },
    {
      "type": "cobblemon:tutor",
      "move": "cobblemon:uproar"
    },
    {
      "type": "cobblemon:tutor",
      "move": "cobblemon:endeavor"
    },
    {
      "type": "cobblemon:tutor",
      "move": "cobblemon:bugbite"
    },
    {
      "type": "cobblemon:tutor",
      "move": "cobblemon:uproar"
    },
    {
      "type": "cobblemon:tm",
      "move": "cobblemon:bugbite"
    },
    {
      "type": "cobblemon:tutor",
      "move": "cobblemon:snore"
    },
    {
      "type": "cobblemon:tutor",
      "move": "cobblemon:stringshot"
    },
    {
      "type": "cobblemon:tutor",
      "move": "cobblemon:endeavor"
    },
    {
      "type": "cobblemon:tm",
      "move": "cobblemon:strugglebug"
    },
    {
      "type": "cobblemon:tutor",
      "move": "cobblemon:uproar"
    },
    {
      "type": "cobblemon:tutor",
      "move": "cobblemon:uproar"
    },
    {
      "type": "cobblemon:tutor",
      "move": "cobblemon:endeavor"
    },
    {
      "type": "cobblemon:tm",
      "move": "cobblemon:lunge"
    },
    {
      "type": "cobblemon:tutor",
      "move": "cobblemon:snore"
    },
    {
      "type": "cobblemon:tutor",
      "move": "cobblemon:uproar"
    },
    {
      "type": "cobblemon:tutor",
      "move": "cobblemon:bugbite"
    },
    {
      "type": "cobblemon:tutor",
      "move": "cobblemon:endeavor"
    },
    {
      "type": "cobblemon:tutor",
      "move": "cobblemon:bugbite"
    },
    {
      "type": "cobblemon:tutor",
      "move": "cobblemon:snore"
    },
    {
      "type": "cobblemon:tm",
      "move": "cobblemon:terablast"
    },
    {
      "type": "cobblemon:tm",
      "move": "cobblemon:endeavor"
    },
    {
      "type": "cobblemon:tutor",
      "move": "cobblemon:endeavor"
    }
  ],
  "nationalPokedexNumber": 401,
  "primaryType": "cobblemon:bug",
  "shoulderEffects": [],
  "shoulderMountable": true,
  "weight": 2.2
}