{
  "values": [
    {
      "id": "cobblemon:growlithe/hisui",
      "required": false
    },
    {
      "id": "cobblemon:arcanine/hisui",
      "required": false
    },
    {
      "id": "cobblemon:voltorb/hisui",
      "required": false
    },
    {
      "id": "cobblemon:electrode/hisui",
      "required": false
    },
    {
      "id": "cobblemon:typhlosion/hisui",
      "required": false
    },
    {
      "id": "cobblemon:qwilfish/hisui",
      "required": false
    },
    {
      "id": "cobblemon:sneasel/hisui",
      "required": false
    },
    {
      "id": "cobblemon:samurott/hisui",
      "required": false
    },
    {
      "id": "cobblemon:lilligant/hisui",
      "required": false
    },
    {
      "id": "cobblemon:zorua/hisui",
      "required": false
    },
    {
      "id": "cobblemon:zoroark/hisui",
      "required": false
    },
    {
      "id": "cobblemon:braviary/hisui",
      "required": false
    },
    {
      "id": "cobblemon:sliggoo/hisui",
      "required": false
    },
    {
      "id": "cobblemon:goodra/hisui",
      "required": false
    },
    {
      "id": "cobblemon:avalugg/hisui",
      "required": false
    },
    {
      "id": "cobblemon:decidueye/hisui",
      "required": false
    }
  ]
}